Metadata-Version: 2.1
Name: mlskeleton
Version: 0.0.2
Summary: A Python package that generates a folder structure for machine learning/deep learning projects
Home-page: https://github.com/Sathiyakugan/mlskeleton#README
Download-URL: https://github.com/asgardeo/mlskeleton/releases
Author: Sathiyakugan B
Author-email: sathiyakugan.bala@gmail.com
License: MIT
Project-URL: Documentation, https://github.com/Sathiyakugan/mlskeleton#README
Project-URL: Bug Tracker, https://github.com/asgardeo/mlskeleton/issues
Project-URL: Source Code, https://github.com/Sathiyakugan/mlskeleton#README
Keywords: machinelearning,deeplearning,folderskeleton,bootstraptemplate,projecttemplate
Classifier: Programming Language :: Python :: 3
Classifier: License :: OSI Approved :: MIT License
Classifier: Operating System :: OS Independent
License-File: LICENSE
